robot_arm_controller/__init__.py
robot_arm_controller/controller.py
robot_arm_controller/control/__init__.py
robot_arm_controller/control/arm_kinematics.py
robot_arm_controller/control/controller_servers.py
robot_arm_controller/tests/__init__.py
robot_arm_controller/tests/test_controller.py
robot_arm_controller/tests/test_kinematics.py
robot_arm_controller/utils/__init__.py
robot_arm_controller/utils/algebra.py
robot_arm_controller/utils/messages.py
robot_arm_controller/utils/prints.py
robot_arm_controller-0.1.9.dist-info/METADATA
robot_arm_controller-0.1.9.dist-info/WHEEL
robot_arm_controller-0.1.9.dist-info/top_level.txt
robot_arm_controller-0.1.9.dist-info/RECORD
