Metadata-Version: 2.1
Name: robot-arm-controller
Version: 0.1.9
Summary: Robot arm controller
Author-email: alberto-abarzua <aabarzua@palvi.cl>
License: MIT
Project-URL: Source Code, https://github.com/alberto-abarzua/Robot-Arm-Control
Keywords: robot,arm,controller
Requires-Python: >=3.11
Requires-Dist: websockets >=11.0.3
Requires-Dist: asyncio >=3.4.3
Requires-Dist: rich >=13.4.2
Requires-Dist: black >=23.3.0
Requires-Dist: isort >=5.12.0
Requires-Dist: flake8 >=6.0.0
Requires-Dist: numpy >=1.25.0
Requires-Dist: flake8-annotations >=3.0.1
Requires-Dist: mypy >=1.4.1
